{
  "vulinfo_id": "JVNDB-2007-000810",
  "title": "JP1/Cm2/Network Node Manager におけるクロスサイトスクリプティングの脆弱性",
  "vulinfo_description": "日立が提供する JP1/Cm2/Network Node Manager (NNM) には、クロスサイトスクリプティングの脆弱性が存在します。  日立が提供する JP1/Cm2/Network Node Manager (NNM) は、ネットワークの構成や障害などを一元的に管理できるソフトウェアです。この NNM には、クロスサイトスクリプティングの脆弱性が存在します。  影響を受けるシステムが複数存在します。 詳しくはベンダの提供する情報をご確認ください。  この脆弱性情報は、情報セキュリティ早期警戒パートナーシップに基づき下記の方が IPA に報告し、JPCERT/CC がベンダとの調整を行いました。 報告者：NTTデータ・セキュリティ株式会社 辻 伸弘 氏",
  "affected": [
    {
      "name": "日立",
      "product_name": "JP1/Cm2/Network Node Manager",
      "cpe": {
        "version": "2.2",
        "text": "cpe:/a:hitachi:jp1_cm2_network_node_manager"
      }
    }
  ],
  "impact": {
    "cvss": [
      {
        "version": "2.0",
        "severity": {
          "type": "Base",
          "text": "Medium"
        },
        "base": "4.3",
        "vector": "AV:N/AC:M/Au:N/C:N/I:P/A:N"
      }
    ],
    "impact_item": "ユーザのウェブブラウザ上で任意のスクリプトを実行される可能性があります。"
  },
  "solution": "アップデートする ベンダが提供する最新版へアップデートしてください。",
  "related": [
    {
      "type": "vendor",
      "name": "Hitachi Software Vulnerability Information",
      "vulinfo_id": "HS07-040",
      "url": "http://www.hitachi-support.com/security_e/vuls_e/HS07-040_e/index-e.html"
    },
    {
      "type": "vendor",
      "name": "ソフトウェア製品セキュリティ情報",
      "vulinfo_id": "HS07-040",
      "url": "http://www.hitachi-support.com/security/vuls/HS07-040/index.html"
    },
    {
      "type": "advisory",
      "name": "JVN",
      "vulinfo_id": "JVN#52846259",
      "url": "http://jvn.jp/jp/JVN%2352846259/index.html"
    }
  ],
  "history": [
    {
      "history_no": "0",
      "date_time": "2018-02-17T01:37:52Z",
      "description": "[2007年12月13日]\\n  掲載"
    }
  ],
  "date_first_published": "2007-12-13T15:02:15+09:00",
  "date_last_updated": "2007-12-13T15:15:23+09:00",
  "date_public": "2007-12-13T00:00:00+09:00"
}
