{
  "vulinfo_id": "JVNDB-2006-000617",
  "title": "複数のメールクライアントソフトにおける、Unicode の取り扱い不備によるディレクトリ・トラバーサルの脆弱性",
  "vulinfo_description": "一部のメールクライアントソフトにおいて、Unicode で書かれた電子メールの添付ファイル名を取り扱う場合、特定の文字列の取り扱いにおいてファイル名の表示が実際と異なることや、ディレクトリトラバーサルが可能な問題があります。 ",
  "affected": [
    {
      "name": "リコー",
      "product_name": "Ridoc Document Router",
      "version_number": [
        "(pro) シリーズ",
        "シリーズ"
      ],
      "cpe": {
        "version": "2.2",
        "text": "cpe:/a:ricoh:ridoc_document_router"
      }
    },
    {
      "name": "リムアーツ",
      "product_name": "Becky! Internet Mail",
      "version_number": [
        "Ver.2.21.04 (2005/08/02 公開) およびそれ以前"
      ],
      "cpe": {
        "version": "2.2",
        "text": "cpe:/a:rimarts_inc.:becky_internet_mail"
      }
    },
    {
      "name": "日本コントロールシステム",
      "product_name": "Paseri",
      "version_number": [
        "Ver1.11.01 およびそれ以前"
      ],
      "cpe": {
        "version": "2.2",
        "text": "cpe:/a:misc:paseri"
      }
    }
  ],
  "impact": {
    "cvss": [
      {
        "version": "2.0",
        "severity": {
          "type": "Base",
          "text": "Medium"
        },
        "base": "5",
        "vector": "AV:N/AC:L/Au:N/C:P/I:N/A:N"
      }
    ],
    "impact_item": "製品により異なりますが、細工されたファイル名を持つ添付ファイルを取り扱うことにより、ファイル名の偽造や、意図しないディレクトリへのファイル作成/上書きが行われる可能性があります。"
  },
  "solution": "ベンダより正式な対策が公開されています。ベンダ情報を参照して適切な対策を実施してください。",
  "related": [
    {
      "type": "vendor",
      "name": "Becky! Internet Mail",
      "vulinfo_id": "Becky! Internet Mail Ver.2 (2.22.00)",
      "url": "http://www.rimarts.co.jp/becky-j.htm"
    },
    {
      "type": "vendor",
      "name": "Becky! Internet Mail",
      "vulinfo_id": "Becky! Internet Mail Ver.2 (2.22.00)",
      "url": "http://www.rimarts.co.jp/becky.htm"
    },
    {
      "type": "vendor",
      "name": "Paseri メールクライアント",
      "vulinfo_id": "Paseri Version 1.12",
      "url": "http://www.nippon-control-system.co.jp/products/paseri/download.html"
    },
    {
      "type": "vendor",
      "name": "製品情報",
      "vulinfo_id": "RidocDocumentSystem メール添付ファイルに関する脆弱性対策について",
      "url": "http://www.ricoh.co.jp/ridoc_ds/rds/download/rds_mail.pdf"
    },
    {
      "type": "advisory",
      "name": "IPA セキュリティセンター",
      "vulinfo_id": "JVN_84775942",
      "url": "http://www.ipa.go.jp/security/vuln/documents/2006/JVN_84775942_MultiMailer.html"
    },
    {
      "type": "advisory",
      "name": "JVN",
      "vulinfo_id": "JVN#84775942",
      "url": "http://jvn.jp/jp/JVN%2384775942/index.html"
    }
  ],
  "history": [
    {
      "history_no": "0",
      "date_time": "2018-02-17T01:37:52Z",
      "description": "[2007年04月01日]\\n  掲載"
    }
  ],
  "date_first_published": "2007-04-01T00:00:00+09:00",
  "date_last_updated": "2007-04-01T00:00:00+09:00",
  "date_public": "2006-05-09T00:00:00+09:00"
}
