{
  "vulinfo_id": "JVNDB-2020-002220",
  "title": "Hitachi Ops Center Common Services における LDAPS の証明書検証に関する脆弱性",
  "vulinfo_description": "Hitachi Ops Center Common Services には、証明書の検証不備の脆弱性が存在します。",
  "affected": [
    {
      "name": "日立",
      "product_name": "Hitachi Ops Center Common Services",
      "version_number": [
        "(海外販売のみ)"
      ],
      "cpe": {
        "version": "2.2",
        "text": "cpe:/a:hitachi:hitachi_ops_center_common_services"
      }
    }
  ],
  "impact": {
    "impact_item": "想定される影響については、ベンダ情報をご確認ください。"
  },
  "solution": "ベンダより正式な対策が公開されています。ベンダ情報を参照して適切な対策を実施してください。",
  "related": [
    {
      "type": "vendor",
      "name": "Hitachi Software Vulnerability Information",
      "vulinfo_id": "hitachi-sec-2020-106",
      "url": "https://www.hitachi.co.jp/Prod/comp/soft1/global/security/info/vuls/hitachi-sec-2020-106/index.html"
    },
    {
      "type": "vendor",
      "name": "ソフトウェア製品セキュリティ情報",
      "vulinfo_id": "hitachi-sec-2020-106",
      "url": "https://www.hitachi.co.jp/Prod/comp/soft1/security/info/vuls/hitachi-sec-2020-106/index.html"
    },
    {
      "type": "cwe",
      "name": "JVNDB",
      "vulinfo_id": "CWE-noinfo",
      "url": "https://www.ipa.go.jp/security/vuln/CWE.html#CWEnoinfo",
      "title": "情報不足"
    }
  ],
  "history": [
    {
      "history_no": "1",
      "date_time": "2020-03-09T02:03:21Z",
      "description": "[2020年03月09日]\\n  掲載"
    }
  ],
  "date_first_published": "2020-03-09T11:03:21+09:00",
  "date_last_updated": "2020-03-09T11:03:21+09:00",
  "date_public": "2020-03-06T00:00:00+09:00"
}
