{
  "id": "TEMP-1007145-ABA7D9",
  "debian_bug": 1007145,
  "packages": [
    {
      "name": "wordpress",
      "status": "open",
      "nodsa": "Minor issues, fix along in next round of updates",
      "nodsa_reason": "postponed",
      "urgency": "not yet assigned",
      "repository": [
        {
          "name": "buster",
          "version": "5.0.15+dfsg1-0+deb10u1"
        },
        {
          "name": "buster-security",
          "version": "5.0.15+dfsg1-0+deb10u1"
        }
      ]
    }
  ]
}
