{
  "vid": "25673e6e-786b-11df-a921-0245fb008c0b",
  "topic": "ziproxy -- security vulnerability in PNG decoder",
  "description": "\n       \u003cp\u003eDaniel Mealha Cabrita reports:\u003c/p\u003e\n       \u003cblockquote cite=\"http://ziproxy.sourceforge.net/#news\"\u003e\n\t \u003cp\u003eFixed security vulnerability (heap-related) in PNG decoder.\n\t   (new bug from 3.1.0)\u003c/p\u003e\n       \u003c/blockquote\u003e\n      ",
  "affects": [
    {
      "name": "ziproxy",
      "range": [
        {
          "ge": "3.1.0"
        },
        {
          "lt": "3.1.1"
        }
      ]
    }
  ],
  "dates": {
    "discovery": "2010-06-15T00:00:00Z",
    "entry": "2010-06-15T00:00:00Z"
  },
  "references": [
    {
      "source": "URL",
      "text": "http://ziproxy.sourceforge.net/#news"
    },
    {
      "source": "MLIST: 201006150731.30474.dancab@gmx.net",
      "text": "http://sourceforge.net/mailarchive/message.php?msg_name=201006150731.30474.dancab%40gmx.net"
    }
  ]
}
