{
  "vid": "5e7f58c3-b3f8-4258-aeb8-795e5e940ff8",
  "topic": "mplayer heap overflow in http requests",
  "description": "\n\t\u003cp\u003eA remotely exploitable heap buffer overflow vulnerability was\n\t  found in MPlayer's URL decoding code.  If an attacker can\n\t  cause MPlayer to visit a specially crafted URL, arbitrary code\n\t  execution with the privileges of the user running MPlayer may\n\t  occur.  A `visit' might be caused by social engineering, or a\n\t  malicious web server could use HTTP redirects which MPlayer\n\t  would then process.\u003c/p\u003e\n      ",
  "affects": [
    {
      "name": "mplayer",
      "range": [
        {
          "lt": "0.92.1"
        }
      ]
    },
    {
      "name": "mplayer-gtk",
      "range": [
        {
          "lt": "0.92.1"
        }
      ]
    },
    {
      "name": "mplayer-esound",
      "range": [
        {
          "lt": "0.92.1"
        }
      ]
    },
    {
      "name": "mplayer-gtk-esound",
      "range": [
        {
          "lt": "0.92.1"
        }
      ]
    }
  ],
  "dates": {
    "discovery": "2004-03-30T00:00:00Z",
    "entry": "2004-03-31T00:00:00Z",
    "modified": "2004-06-27T00:00:00Z"
  },
  "references": [
    {
      "source": "URL",
      "text": "http://www.mplayerhq.hu/homepage/design6/news.html"
    },
    {
      "source": "FreebsdPR",
      "text": "ports/64974"
    },
    {
      "source": "MLIST",
      "text": "http://marc.theaimsgroup.com/?l=bugtraq\u0026m=108066964709058"
    }
  ]
}
