{
  "vid": "88a77ad8-77b1-11e7-b5af-a4badb2f4699",
  "topic": "Varnish -- Denial of service vulnerability",
  "description": "\n\t\u003cp\u003ephk reports:\u003c/p\u003e\n\t\u003cblockquote cite=\"https://varnish-cache.org/security/VSV00001.html\"\u003e\n\t  \u003cp\u003eA wrong if statement in the varnishd source code means that\n\t    particular invalid requests from the client can trigger an assert.\u003c/p\u003e\n\t\u003c/blockquote\u003e\n      ",
  "affects": [
    {
      "name": "varnish4",
      "range": [
        {
          "lt": "4.0.5",
          "ge": "4.0.1"
        },
        {
          "lt": "4.1.8",
          "ge": "4.1.0"
        }
      ]
    },
    {
      "name": "varnish5",
      "range": [
        {
          "lt": "5.0.1"
        },
        {
          "lt": "5.1.3",
          "ge": "5.1.0"
        }
      ]
    }
  ],
  "dates": {
    "discovery": "2017-08-02T00:00:00Z",
    "entry": "2017-08-02T00:00:00Z"
  },
  "references": [
    {
      "source": "URL",
      "text": "https://varnish-cache.org/security/VSV00001.html"
    }
  ]
}
