{
  "vid": "af0296be-2455-11d8-82e5-0020ed76ef5a",
  "topic": "fetchmail -- address parsing vulnerability",
  "description": "\n\t\u003cp\u003eFetchmail can be crashed by a malicious email message.\u003c/p\u003e\n      ",
  "affects": [
    {
      "name": "fetchmail",
      "range": [
        {
          "le": "6.2.0"
        }
      ]
    }
  ],
  "dates": {
    "discovery": "2003-10-25T00:00:00Z",
    "entry": "2003-10-25T00:00:00Z",
    "modified": "2012-09-04T00:00:00Z"
  },
  "references": [
    {
      "source": "URL",
      "text": "http://security.e-matters.de/advisories/052002.html"
    }
  ]
}
