{
  "vid": "b80f039d-579e-4b82-95ad-b534a709f220",
  "topic": "bro -- \"Magellan\" remote code execution vulnerability in bundled sqlite",
  "description": "\n\t\u003cp\u003eBro Network security Monitor reports:\u003c/p\u003e\n\t\u003cblockquote cite=\"https://www.bro.org/download/NEWS.bro.html\"\u003e\n\t  \u003cp\u003eBro 2.6.1 updates the embedded SQLite to version 3.26.0\n\t  to address the \"Magellan\" remote code execution vulnerability.\n\t  The stock Bro configuration/scripts don't use SQLite by\n\t  default, but custom user scripts/packages may.\u003c/p\u003e\n\t\u003c/blockquote\u003e\n      ",
  "affects": [
    {
      "name": "bro",
      "range": [
        {
          "lt": "2.6.1"
        }
      ]
    }
  ],
  "dates": {
    "discovery": "2018-12-01T00:00:00Z",
    "entry": "2018-12-20T00:00:00Z"
  },
  "references": [
    {
      "source": "URL",
      "text": "https://www.bro.org/download/NEWS.bro.html"
    }
  ]
}
