{
  "vid": "c290f093-c89e-11e6-821e-68f7288bdf41",
  "topic": "Pligg CMS -- XSS Vulnerability",
  "description": "\n\t\u003cp\u003eNetsparker reports: \u003c/p\u003e\n\t\u003cblockquote cite=\"https://www.netsparker.com/web-applications-advisories/ns-15-011-xss-vulnerability-identified-in-pligg-cms/\"\u003e\n\t  \u003cp\u003eProof of Concept URL for XSS in Pligg CMS:\u003c/p\u003e\n\t  \u003cp\u003ePage: groups.php\u003c/p\u003e\n\t  \u003cp\u003eParameter Name: keyword\u003c/p\u003e\n\t  \u003cp\u003eParameter Type: GET\u003c/p\u003e\n\t  \u003cp\u003eAttack Pattern: http://example.com/pligg-cms-2.0.2/groups.php?view=search\u0026amp;keyword='+alert(0x000D82)+'\u003c/p\u003e\n\t  \u003cp\u003eFor more information on cross-site scripting vulnerabilities read the article Cross-site Scripting (XSS).\u003c/p\u003e\n\t\u003c/blockquote\u003e\n      ",
  "affects": [
    {
      "name": "pligg",
      "range": [
        {
          "le": "2.0.2,1"
        }
      ]
    }
  ],
  "dates": {
    "discovery": "2015-05-13T00:00:00Z",
    "entry": "2016-12-22T00:00:00Z"
  },
  "references": [
    {
      "source": "URL",
      "text": "https://www.netsparker.com/web-applications-advisories/ns-15-011-xss-vulnerability-identified-in-pligg-cms/"
    }
  ]
}
