{
  "vid": "d67b517d-8214-11de-88ea-001a4d49522b",
  "topic": "bugzilla -- product name information leak",
  "description": "\n\t\u003cp\u003eA Bugzilla Security Advisory reports:\u003c/p\u003e\n\t\u003cblockquote cite=\"http://www.bugzilla.org/security/3.4/\"\u003e\n\t  \u003cp\u003eNormally, users are only supposed to see products that\n\t    they can file bugs against in the \"Product\" drop-down on\n\t    the bug-editing page. Instead, users were being shown all\n\t    products, even those that they normally could not see. Any\n\t    user who could edit any bug could see all product\n\t    names.\u003c/p\u003e\n\t\u003c/blockquote\u003e\n      ",
  "affects": [
    {
      "name": "bugzilla",
      "range": [
        {
          "lt": "3.4.1",
          "gt": "3.3.4"
        }
      ]
    }
  ],
  "dates": {
    "discovery": "2009-07-30T00:00:00Z",
    "entry": "2009-08-05T00:00:00Z"
  },
  "references": [
    {
      "source": "URL",
      "text": "http://www.bugzilla.org/security/3.4/"
    }
  ]
}
