{
  "vid": "f14ce57f-6dc8-11e8-a671-001999f8d30b",
  "topic": "asterisk -- Infinite loop when reading iostreams",
  "description": "\n\t\u003cp\u003eThe Asterisk project reports:\u003c/p\u003e\n\t\u003cblockquote cite=\"http://www.asterisk.org/downloads/security-advisories\"\u003e\n\t  \u003cp\u003eWhen connected to Asterisk via TCP/TLS if the client\n\t  abruptly disconnects, or sends a specially crafted message\n\t  then Asterisk gets caught in an infinite loop while trying\n\t  to read the data stream. Thus rendering the system as\n\t  unusable.\u003c/p\u003e\n\t\u003c/blockquote\u003e\n      ",
  "affects": [
    {
      "name": "asterisk15",
      "range": [
        {
          "lt": "15.4.1"
        }
      ]
    }
  ],
  "dates": {
    "discovery": "2018-06-11T00:00:00Z",
    "entry": "2018-06-11T00:00:00Z"
  },
  "references": [
    {
      "source": "URL",
      "text": "https://downloads.asterisk.org/pub/security/AST-2018-007.html"
    }
  ]
}
